dadinet/__init__.py
dadinet/__main__.py
dadinet/custom_models.py
dadinet/dadi_dem_models.py
dadinet/generate_data.py
dadinet/plot.py
dadinet/portik_models_2d.py
dadinet/portik_models_2d_update.py
dadinet/portik_models_3d.py
dadinet/portik_models_3d_update.py
dadinet/predict.py
dadinet/train.py
project_ml_ab3nzac1yc_hatch-1.0.1.dist-info/METADATA
project_ml_ab3nzac1yc_hatch-1.0.1.dist-info/WHEEL
project_ml_ab3nzac1yc_hatch-1.0.1.dist-info/entry_points.txt
project_ml_ab3nzac1yc_hatch-1.0.1.dist-info/RECORD
