Metadata-Version: 2.1
Name: project-ml-AB3NzaC1yc-hatch
Version: 1.0.1
Summary: Machine learning applications for dadi
Author: Connie Sun
Author-email: Linh Tran <lnt@email.arizona.edu>
Requires-Python: >=3.7
Requires-Dist: flake8
Requires-Dist: mapie==0.3.1
Requires-Dist: mypy
Requires-Dist: project-base-ab3nzac1yc-setuptools
Requires-Dist: pylint
Requires-Dist: pytest
Requires-Dist: pytest-flake8
Requires-Dist: pytest-mypy
Requires-Dist: pytest-pylint
Requires-Dist: scikit-learn==1.0.2
